{
    "test_parameters":{
        "test_timeout": 200,
        "load_blank_db": false,
        "load_factory_default_db": true,
        "load_custom_db": false,
        "custom_db": "DFLT_ETH1_GEN",
        "email_list_production": "konikofi@candelatech.com,greearb@candelatech.com,logan.lipke@candelatech.com,chuck.rekiere@candelatech.com,",
        "host_ip_production": "192.168.95.6",
        "email_list_test": "chuck.rekiere@candelatech.com",
        "host_ip_test": "192.168.95.6",
        "lf_mgr": "192.168.100.116",
        "email_title_txt": "Lanforge QA Testing CT-US-001",
        "email_txt": "Lanforge QA Testing CT-US-001 "
    },
    "test_network":{
        "http_test_ip": "10.40.0.10",
        "ftp_test_ip": "10.40.0.10",
        "test_ip": "192.168.0.104"
    },
    "radio_dict":{
        "RADIO_0_CFG":{"KEY":"RADIO_0_CFG","RADIO":"wiphy0","STATIONS":"4","SSID":"ct523c-vap","PASSWD":"ct523c-vap","SECURITY":"wpa2"},
        "RADIO_1_CFG":{"KEY":"RADIO_1_CFG","RADIO":"wiphy1","STATIONS":"4","SSID":"ct523c-vap","PASSWD":"ct523c-vap","SECURITY":"wpa2"}        
    }
}
			
	
		
	